{
    "type": "results", 
    "job_id": "05006.fos", 
    "task_id": "a05", 
    "chasm_output": {
        "factor_of_safety": [
            1.1858, 
            1.25889, 
            1.26306, 
            1.29391, 
            1.33324, 
            1.31286, 
            1.32114, 
            1.37703, 
            1.3859, 
            1.3936, 
            1.40043, 
            1.40592, 
            1.41111, 
            1.4154, 
            1.41931, 
            1.42298, 
            1.42649, 
            1.42986, 
            1.43233, 
            1.43438, 
            1.43633, 
            1.43821, 
            1.44, 
            1.44172, 
            1.43269, 
            1.44444, 
            1.4456, 
            1.44676, 
            1.44788, 
            1.44866, 
            1.43994, 
            1.44971, 
            1.44971, 
            1.44971, 
            1.44971, 
            1.44971, 
            1.44971, 
            1.44971, 
            1.44971, 
            1.44753, 
            1.44971, 
            1.44971, 
            1.44971, 
            1.44971, 
            1.44971, 
            1.44971, 
            1.44971, 
            1.44971, 
            1.44971, 
            1.44971, 
            1.44971, 
            1.44971, 
            1.44971, 
            1.44971, 
            1.44971, 
            1.44971, 
            1.44971, 
            1.44971, 
            1.44971, 
            1.44971, 
            1.44971, 
            1.44971, 
            1.44971, 
            1.44971, 
            1.44971, 
            1.44971, 
            1.44971, 
            1.44971, 
            1.44971, 
            1.44971, 
            1.44971, 
            1.44971, 
            1.44971, 
            1.44971, 
            1.44971, 
            1.44971, 
            1.44971, 
            1.44971, 
            1.44971, 
            1.44971, 
            1.44971, 
            1.44971, 
            1.44971, 
            1.44971, 
            1.44971, 
            1.44971, 
            1.44971, 
            1.44971, 
            1.44971, 
            1.44971, 
            1.44971, 
            1.44971, 
            1.44971, 
            1.44971, 
            1.44971, 
            1.44971, 
            1.44971, 
            1.44971, 
            1.44971, 
            1.44971, 
            1.44971, 
            1.44971, 
            1.44971, 
            1.44971, 
            1.44971, 
            1.44971, 
            1.44971, 
            1.44971, 
            1.44971, 
            1.44971, 
            1.44971, 
            1.44971, 
            1.44971, 
            1.44971, 
            1.44971, 
            1.44971, 
            1.44971, 
            1.44971, 
            1.44971, 
            1.44971, 
            1.44971, 
            1.44971, 
            1.44971, 
            1.44971, 
            1.44971, 
            1.44971, 
            1.44971, 
            1.44971, 
            1.44971, 
            1.44971, 
            1.44971, 
            1.44971, 
            1.44971, 
            1.44971, 
            1.44971, 
            1.44971, 
            1.44971, 
            1.44971, 
            1.44971, 
            1.44971, 
            1.44971, 
            1.44971, 
            1.44971, 
            1.44971, 
            1.44971, 
            1.44971, 
            1.44971, 
            1.44971, 
            1.44971, 
            1.44971, 
            1.44971, 
            1.44971, 
            1.44971, 
            1.44971, 
            1.44971, 
            1.44971, 
            1.44971, 
            1.44971, 
            1.44971, 
            1.44971, 
            1.44971, 
            1.44971, 
            1.44971, 
            1.44971, 
            1.44971, 
            1.44971, 
            1.44971, 
            1.44971, 
            1.44971, 
            1.44971, 
            1.44971, 
            1.44971, 
            1.44395, 
            1.43901, 
            1.43853, 
            1.43573, 
            1.43293, 
            1.42944, 
            1.41926, 
            1.40549, 
            1.38812, 
            1.35881, 
            1.33982, 
            1.30442, 
            1.28794, 
            1.28428, 
            1.26987, 
            1.21057, 
            1.16699, 
            1.16935, 
            1.16903, 
            1.15889, 
            1.1803, 
            1.18622, 
            1.24976, 
            1.32456, 
            1.36692, 
            1.37872, 
            1.38827, 
            1.39667, 
            1.40145, 
            1.38521, 
            1.39886, 
            1.38519, 
            1.39766, 
            1.3925, 
            1.39485, 
            1.3897, 
            1.4033, 
            1.39546, 
            1.39836, 
            1.40096, 
            1.39931, 
            1.40086, 
            1.38997, 
            1.39538, 
            1.39093, 
            1.39591, 
            1.41173, 
            1.39576, 
            1.40336, 
            1.40401, 
            1.40062, 
            1.40073, 
            1.4033, 
            1.40397, 
            1.40694, 
            1.40272, 
            1.41872, 
            1.41764, 
            1.40921, 
            1.41497, 
            1.4231, 
            1.4144, 
            1.4166, 
            1.40999, 
            1.41388, 
            1.41208, 
            1.42746, 
            1.41785, 
            1.41141, 
            1.43862, 
            1.43471, 
            1.43964, 
            1.42638, 
            1.42903, 
            1.44841, 
            1.43296, 
            1.43444, 
            1.44971, 
            1.44299, 
            1.44971, 
            1.44971, 
            1.44213, 
            1.44971, 
            1.44652, 
            1.44971, 
            1.44971, 
            1.44971, 
            1.44971, 
            1.44724, 
            1.44971, 
            1.44971, 
            1.44971, 
            1.44971, 
            1.44971, 
            1.44971, 
            1.44971, 
            1.44971, 
            1.44971, 
            1.44971, 
            1.44971, 
            1.44971, 
            1.44971, 
            1.44971, 
            1.44971, 
            1.44971, 
            1.44971, 
            1.44971, 
            1.44971, 
            1.44971, 
            1.44971, 
            1.44971, 
            1.44971, 
            1.44971, 
            1.44971, 
            1.44971, 
            1.44971, 
            1.44971, 
            1.44971, 
            1.44971, 
            1.44971, 
            1.44971, 
            1.44971, 
            1.44971, 
            1.44971, 
            1.44971, 
            1.44971, 
            1.44971, 
            1.44971, 
            1.44971, 
            1.44971, 
            1.44971, 
            1.44971, 
            1.44971, 
            1.44971, 
            1.44971, 
            1.44971, 
            1.44971, 
            1.44971, 
            1.44971, 
            1.44971, 
            1.44971, 
            1.44971, 
            1.44971, 
            1.44971, 
            1.44971, 
            1.44971, 
            1.44971, 
            1.44971, 
            1.44971, 
            1.44971, 
            1.44971, 
            1.44971, 
            1.44971, 
            1.44971, 
            1.44971, 
            1.44971, 
            1.44971, 
            1.44971, 
            1.44971, 
            1.44971, 
            1.44971, 
            1.44971, 
            1.44971, 
            1.44971, 
            1.44971, 
            1.44971, 
            1.44971, 
            1.44971, 
            1.44971, 
            1.44971, 
            1.44971, 
            1.44971, 
            1.44971, 
            1.44971, 
            1.44971, 
            1.44971, 
            1.44971, 
            1.44971, 
            1.44971, 
            1.44971, 
            1.44971, 
            1.44971, 
            1.44971, 
            1.44971, 
            1.44971, 
            1.44971, 
            1.44971, 
            1.44971, 
            1.44971
        ]
    }
}